pysplishsplash.cpython-310-darwin.so
pysplishsplash-2.15.1.data/data/bin/resources/shaders/fs_smooth.glsl
pysplishsplash-2.15.1.data/data/bin/resources/shaders/mini.frag
pysplishsplash-2.15.1.data/data/bin/resources/shaders/vs_points_vector.glsl
pysplishsplash-2.15.1.data/data/bin/resources/shaders/fs_points_colormap.glsl
pysplishsplash-2.15.1.data/data/bin/resources/shaders/vs_points_scalar.glsl
pysplishsplash-2.15.1.data/data/bin/resources/shaders/mini_screen.frag
pysplishsplash-2.15.1.data/data/bin/resources/shaders/fs_points.glsl
pysplishsplash-2.15.1.data/data/bin/resources/shaders/vs_smooth.glsl
pysplishsplash-2.15.1.data/data/bin/resources/shaders/mini.vert
pysplishsplash-2.15.1.data/data/bin/resources/shaders/mini_screen.vert
pysplishsplash-2.15.1.data/data/bin/resources/emitter_boundary/EmitterCylinder.obj
pysplishsplash-2.15.1.data/data/bin/resources/emitter_boundary/EmitterBox.obj
pysplishsplash-2.15.1.data/data/bin/resources/fonts/Roboto-Medium.ttf
pysplishsplash-2.15.1.data/data/bin/data/Scenes/ScriptTest.py
pysplishsplash-2.15.1.data/data/bin/data/Scenes/AnimatedBody_2D.py
pysplishsplash-2.15.1.data/data/bin/data/Scenes/Empty.json
pysplishsplash-2.15.1.data/data/bin/data/Scenes/MultiPhaseColoring.json
pysplishsplash-2.15.1.data/data/bin/data/Scenes/Emitter.json
pysplishsplash-2.15.1.data/data/bin/data/Scenes/DoubleDamBreakWithSphere.json
pysplishsplash-2.15.1.data/data/bin/data/Scenes/GridModel_Koschier2017.json
pysplishsplash-2.15.1.data/data/bin/data/Scenes/CompressibleSPH_ICSPH.json
pysplishsplash-2.15.1.data/data/bin/data/Scenes/CompressibleSPH_PF.json
pysplishsplash-2.15.1.data/data/bin/data/Scenes/CompressibleSPH_WCSPH.json
pysplishsplash-2.15.1.data/data/bin/data/Scenes/BucklingModel_Takahashi2015.json
pysplishsplash-2.15.1.data/data/bin/data/Scenes/SurfaceTension_CoveredSphere_JWL+23.json
pysplishsplash-2.15.1.data/data/bin/data/Scenes/DamBreakModel.json
pysplishsplash-2.15.1.dist-info/RECORD
pysplishsplash-2.15.1.dist-info/WHEEL
pysplishsplash-2.15.1.dist-info/entry_points.txt
pysplishsplash-2.15.1.dist-info/top_level.txt
pysplishsplash-2.15.1.dist-info/METADATA
pysplishsplash-2.15.1.dist-info/licenses/LICENSE
