Metadata-Version: 2.4
Name: pySPlisHSPlasH
Version: 2.15.1
Summary: SPlisHSPlasH Project Python Bindings
Home-page: https://github.com/InteractiveComputerGraphics/SPlisHSPlasH
Author: Interactive Computer Graphics
Author-email: 
License: MIT
Keywords: sph fluids sph-fluids smoothed-particle-hydrodynamics fluid-simulation fluid-dynamics multiphase-flow viscous-fluids deformable-solids simulation
License-File: LICENSE
Requires-Dist: numpy
Dynamic: author
Dynamic: description
Dynamic: description-content-type
Dynamic: home-page
Dynamic: keywords
Dynamic: license
Dynamic: license-file
Dynamic: requires-dist
Dynamic: summary
